springlabs_pypi/__init__.py
springlabs_pypi/main.py
springlabs_pypi/utils.py
springlabs_pypi/scripts/__init__.py
springlabs_pypi/scripts/springlabs_python.py
springlabs_python/__init__.py
springlabs_python/main.py
springlabs_python/utils.py
springlabs_python/scripts/__init__.py
springlabs_python/scripts/springlabs_python.py
springlabs_python-0.8.6.dist-info/LICENSE
springlabs_python-0.8.6.dist-info/METADATA
springlabs_python-0.8.6.dist-info/WHEEL
springlabs_python-0.8.6.dist-info/entry_points.txt
springlabs_python-0.8.6.dist-info/top_level.txt
springlabs_python-0.8.6.dist-info/RECORD
