Metadata-Version: 2.1
Name: springlabs-python
Version: 0.8.6
Summary: Springlabs Projects Python Standard
Home-page: https://springlabs.ai/
Author: Alejandro Barcenas
Author-email: barcenas.r.2510@gmail.com
License: UNKNOWN
Project-URL: Source Code, https://gitlab.com/AlejandroBarcenas/springlabs-python-cli
Platform: UNKNOWN
Classifier: Programming Language :: Python :: 3
Classifier: License :: OSI Approved :: MIT License
Classifier: Operating System :: OS Independent
Requires-Python: >=3.6
Requires-Dist: click (==7.1.2)
Requires-Dist: requests (==2.24.0)
